lab8/ALU.v
module ALU
(
	input [11:0] a, b, 
	input [2:0] command,
	output [11:0] res,
	output reg [3:0] flags
);
	
  reg [11:0] result;
  reg [11:0] l_b;				// local b 
	
  always @(a, b, command) begin
	
	flags = 4'b0000;
	
	case (command)
	  'd0: 						// addition
	    begin
		  result = a + b;		
		  flags[0] = (a[11] == 1 && b[11] == 1 && result[11] == 0) || (a[11] == 0 && b[11] == 0 && result[11] == 1);
		end
	  'd1: 						// subtraction
	    begin
		  l_b = ~b + 1'b1;		// convert to negative
		  result = a + l_b;		
		  flags[0] = (a[11] == 1 && b[11] == 1 && result[11] == 0) || (a[11] == 0 && b[11] == 0 && result[11] == 1);
		end
	  'd2: result = a * b;		// multiplication
	  'd3: result = a / b;		// division
	  'd4: result = a & b;		// Logical AND
	  'd5: result = a | b;		// Logical OR
	  'd6: result = ~a & b;		// ~A&B
	  'd7: result = ~a | b;		// ~A|B
	endcase
	
	if (result == 0) 
	  flags[3] = 1;				// Zero flag
	  
	if (result[0] == 0)
	  flags[2] = 1;				// Parity flag
	  
	flags[1] = result[11];	  	// Sign flag
	
  end
  
  assign res = result[11:0];

endmodule

lab8/ALU_tb.v
`timescale 1ns/1ns

module ALU_TB();

  reg [11:0] a, b;
  reg [2:0] command;
  wire [11:0] res;
  wire [3:0] flags;
  
  ALU alu_sample( .a(a), .b(b), .command(command), .res(res), .flags(flags) );
  
  initial begin
    $dumpfile("alu_tb_out.vcd");
	$dumpvars(0, ALU_TB);  
  end
  
  initial begin
    a = 0;
	b = 0;
	command = 0;
	#400 $finish;
  end  
  
  always #5 begin
    a = a + 1;
	b = b + 2;
  end;
  
  always #20 command = command + 1;
  
endmodule

lab8/alu_tb_out.vcd
$date
	Wed Dec 13 21:33:12 2023
$end
$version
	Icarus Verilog
$end
$timescale
	1ns
$end
$scope module ALU_TB $end
$var wire 12 ! res [11:0] $end
$var wire 4 " flags [3:0] $end
$var reg 12 # a [11:0] $end
$var reg 12 $ b [11:0] $end
$var reg 3 % command [2:0] $end
$scope module alu_sample $end
$var wire 12 & a [11:0] $end
$var wire 12 ' b [11:0] $end
$var wire 3 ( command [2:0] $end
$var wire 12 ) res [11:0] $end
$var reg 4 * flags [3:0] $end
$var reg 12 + l_b [11:0] $end
$var reg 12 , result [11:0] $end
$upscope $end
$upscope $end
$enddefinitions $end
#0
$dumpvars
b0 ,
bx +
b1100 *
b0 )
b0 (
b0 '
b0 &
b0 %
b0 $
b0 #
b1100 "
b0 !
$end
#5
b11 !
b11 )
b11 ,
b0 "
b0 *
b10 $
b10 '
b1 #
b1 &
#10
b100 "
b100 *
b110 !
b110 )
b110 ,
b100 $
b100 '
b10 #
b10 &
#15
b1001 !
b1001 )
b1001 ,
b0 "
b0 *
b110 $
b110 '
b11 #
b11 &
#20
b111 "
b111 *
b111111111100 !
b111111111100 )
b111111111100 ,
b111111111000 +
b1000 $
b1000 '
b100 #
b100 &
b1 %
b1 (
#25
b111111111011 !
b111111111011 )
b111111111011 ,
b111111110110 +
b11 "
b11 *
b1010 $
b1010 '
b101 #
b101 &
#30
b111111111010 !
b111111111010 )
b111111111010 ,
b111111110100 +
b111 "
b111 *
b1100 $
b1100 '
b110 #
b110 &
#35
b111111111001 !
b111111111001 )
b111111111001 ,
b111111110010 +
b11 "
b11 *
b1110 $
b1110 '
b111 #
b111 &
#40
b10000000 !
b10000000 )
b10000000 ,
b100 "
b100 *
b10000 $
b10000 '
b1000 #
b1000 &
b10 %
b10 (
#45
b10100010 !
b10100010 )
b10100010 ,
b100 "
b100 *
b10010 $
b10010 '
b1001 #
b1001 &
#50
b11001000 !
b11001000 )
b11001000 ,
b100 "
b100 *
b10100 $
b10100 '
b1010 #
b1010 &
#55
b11110010 !
b11110010 )
b11110010 ,
b100 "
b100 *
b10110 $
b10110 '
b1011 #
b1011 &
#60
b0 !
b0 )
b0 ,
b1100 "
b1100 *
b11000 $
b11000 '
b1100 #
b1100 &
b11 %
b11 (
#65
b1100 "
b1100 *
b11010 $
b11010 '
b1101 #
b1101 &
#70
b1100 "
b1100 *
b11100 $
b11100 '
b1110 #
b1110 &
#75
b1100 "
b1100 *
b11110 $
b11110 '
b1111 #
b1111 &
#80
b1100 "
b1100 *
b100000 $
b100000 '
b10000 #
b10000 &
b100 %
b100 (
#85
b1100 "
b1100 *
b100010 $
b100010 '
b10001 #
b10001 &
#90
b1100 "
b1100 *
b100100 $
b100100 '
b10010 #
b10010 &
#95
b10 !
b10 )
b10 ,
b100 "
b100 *
b100110 $
b100110 '
b10011 #
b10011 &
#100
b111100 !
b111100 )
b111100 ,
b100 "
b100 *
b101000 $
b101000 '
b10100 #
b10100 &
b101 %
b101 (
#105
b111111 !
b111111 )
b111111 ,
b0 "
b0 *
b101010 $
b101010 '
b10101 #
b10101 &
#110
b100 "
b100 *
b111110 !
b111110 )
b111110 ,
b101100 $
b101100 '
b10110 #
b10110 &
#115
b111111 !
b111111 )
b111111 ,
b0 "
b0 *
b101110 $
b101110 '
b10111 #
b10111 &
#120
b100 "
b100 *
b100000 !
b100000 )
b100000 ,
b110000 $
b110000 '
b11000 #
b11000 &
b110 %
b110 (
#125
b100010 !
b100010 )
b100010 ,
b100 "
b100 *
b110010 $
b110010 '
b11001 #
b11001 &
#130
b100100 !
b100100 )
b100100 ,
b100 "
b100 *
b110100 $
b110100 '
b11010 #
b11010 &
#135
b100 "
b100 *
b110110 $
b110110 '
b11011 #
b11011 &
#140
b111111111011 !
b111111111011 )
b111111111011 ,
b10 "
b10 *
b111000 $
b111000 '
b11100 #
b11100 &
b111 %
b111 (
#145
b111111111010 !
b111111111010 )
b111111111010 ,
b110 "
b110 *
b111010 $
b111010 '
b11101 #
b11101 &
#150
b111111111101 !
b111111111101 )
b111111111101 ,
b10 "
b10 *
b111100 $
b111100 '
b11110 #
b11110 &
#155
b111111111110 !
b111111111110 )
b111111111110 ,
b110 "
b110 *
b111110 $
b111110 '
b11111 #
b11111 &
#160
b1100000 !
b1100000 )
b1100000 ,
b100 "
b100 *
b1000000 $
b1000000 '
b100000 #
b100000 &
b0 %
b0 (
#165
b1100011 !
b1100011 )
b1100011 ,
b0 "
b0 *
b1000010 $
b1000010 '
b100001 #
b100001 &
#170
b100 "
b100 *
b1100110 !
b1100110 )
b1100110 ,
b1000100 $
b1000100 '
b100010 #
b100010 &
#175
b1101001 !
b1101001 )
b1101001 ,
b0 "
b0 *
b1000110 $
b1000110 '
b100011 #
b100011 &
#180
b111 "
b111 *
b111111011100 !
b111111011100 )
b111111011100 ,
b111110111000 +
b1001000 $
b1001000 '
b100100 #
b100100 &
b1 %
b1 (
#185
b111111011011 !
b111111011011 )
b111111011011 ,
b111110110110 +
b11 "
b11 *
b1001010 $
b1001010 '
b100101 #
b100101 &
#190
b111111011010 !
b111111011010 )
b111111011010 ,
b111110110100 +
b111 "
b111 *
b1001100 $
b1001100 '
b100110 #
b100110 &
#195
b111111011001 !
b111111011001 )
b111111011001 ,
b111110110010 +
b11 "
b11 *
b1001110 $
b1001110 '
b100111 #
b100111 &
#200
b110010000000 !
b110010000000 )
b110010000000 ,
b110 "
b110 *
b1010000 $
b1010000 '
b101000 #
b101000 &
b10 %
b10 (
#205
b110100100010 !
b110100100010 )
b110100100010 ,
b110 "
b110 *
b1010010 $
b1010010 '
b101001 #
b101001 &
#210
b110111001000 !
b110111001000 )
b110111001000 ,
b110 "
b110 *
b1010100 $
b1010100 '
b101010 #
b101010 &
#215
b111001110010 !
b111001110010 )
b111001110010 ,
b110 "
b110 *
b1010110 $
b1010110 '
b101011 #
b101011 &
#220
b0 !
b0 )
b0 ,
b1100 "
b1100 *
b1011000 $
b1011000 '
b101100 #
b101100 &
b11 %
b11 (
#225
b1100 "
b1100 *
b1011010 $
b1011010 '
b101101 #
b101101 &
#230
b1100 "
b1100 *
b1011100 $
b1011100 '
b101110 #
b101110 &
#235
b1100 "
b1100 *
b1011110 $
b1011110 '
b101111 #
b101111 &
#240
b100000 !
b100000 )
b100000 ,
b100 "
b100 *
b1100000 $
b1100000 '
b110000 #
b110000 &
b100 %
b100 (
#245
b100 "
b100 *
b1100010 $
b1100010 '
b110001 #
b110001 &
#250
b100 "
b100 *
b1100100 $
b1100100 '
b110010 #
b110010 &
#255
b100010 !
b100010 )
b100010 ,
b100 "
b100 *
b1100110 $
b1100110 '
b110011 #
b110011 &
#260
b1111100 !
b1111100 )
b1111100 ,
b100 "
b100 *
b1101000 $
b1101000 '
b110100 #
b110100 &
b101 %
b101 (
#265
b1111111 !
b1111111 )
b1111111 ,
b0 "
b0 *
b1101010 $
b1101010 '
b110101 #
b110101 &
#270
b100 "
b100 *
b1111110 !
b1111110 )
b1111110 ,
b1101100 $
b1101100 '
b110110 #
b110110 &
#275
b1111111 !
b1111111 )
b1111111 ,
b0 "
b0 *
b1101110 $
b1101110 '
b110111 #
b110111 &
#280
b100 "
b100 *
b1000000 !
b1000000 )
b1000000 ,
b1110000 $
b1110000 '
b111000 #
b111000 &
b110 %
b110 (
#285
b1000010 !
b1000010 )
b1000010 ,
b100 "
b100 *
b1110010 $
b1110010 '
b111001 #
b111001 &
#290
b1000100 !
b1000100 )
b1000100 ,
b100 "
b100 *
b1110100 $
b1110100 '
b111010 #
b111010 &
#295
b100 "
b100 *
b1110110 $
b1110110 '
b111011 #
b111011 &
#300
b111111111011 !
b111111111011 )
b111111111011 ,
b10 "
b10 *
b1111000 $
b1111000 '
b111100 #
b111100 &
b111 %
b111 (
#305
b111111111010 !
b111111111010 )
b111111111010 ,
b110 "
b110 *
b1111010 $
b1111010 '
b111101 #
b111101 &
#310
b111111111101 !
b111111111101 )
b111111111101 ,
b10 "
b10 *
b1111100 $
b1111100 '
b111110 #
b111110 &
#315
b111111111110 !
b111111111110 )
b111111111110 ,
b110 "
b110 *
b1111110 $
b1111110 '
b111111 #
b111111 &
#320
b11000000 !
b11000000 )
b11000000 ,
b100 "
b100 *
b10000000 $
b10000000 '
b1000000 #
b1000000 &
b0 %
b0 (
#325
b11000011 !
b11000011 )
b11000011 ,
b0 "
b0 *
b10000010 $
b10000010 '
b1000001 #
b1000001 &
#330
b100 "
b100 *
b11000110 !
b11000110 )
b11000110 ,
b10000100 $
b10000100 '
b1000010 #
b1000010 &
#335
b11001001 !
b11001001 )
b11001001 ,
b0 "
b0 *
b10000110 $
b10000110 '
b1000011 #
b1000011 &
#340
b111 "
b111 *
b111110111100 !
b111110111100 )
b111110111100 ,
b111101111000 +
b10001000 $
b10001000 '
b1000100 #
b1000100 &
b1 %
b1 (
#345
b111110111011 !
b111110111011 )
b111110111011 ,
b111101110110 +
b11 "
b11 *
b10001010 $
b10001010 '
b1000101 #
b1000101 &
#350
b111110111010 !
b111110111010 )
b111110111010 ,
b111101110100 +
b111 "
b111 *
b10001100 $
b10001100 '
b1000110 #
b1000110 &
#355
b111110111001 !
b111110111001 )
b111110111001 ,
b111101110010 +
b11 "
b11 *
b10001110 $
b10001110 '
b1000111 #
b1000111 &
#360
b100010000000 !
b100010000000 )
b100010000000 ,
b110 "
b110 *
b10010000 $
b10010000 '
b1001000 #
b1001000 &
b10 %
b10 (
#365
b100110100010 !
b100110100010 )
b100110100010 ,
b110 "
b110 *
b10010010 $
b10010010 '
b1001001 #
b1001001 &
#370
b101011001000 !
b101011001000 )
b101011001000 ,
b110 "
b110 *
b10010100 $
b10010100 '
b1001010 #
b1001010 &
#375
b101111110010 !
b101111110010 )
b101111110010 ,
b110 "
b110 *
b10010110 $
b10010110 '
b1001011 #
b1001011 &
#380
b0 !
b0 )
b0 ,
b1100 "
b1100 *
b10011000 $
b10011000 '
b1001100 #
b1001100 &
b11 %
b11 (
#385
b1100 "
b1100 *
b10011010 $
b10011010 '
b1001101 #
b1001101 &
#390
b1100 "
b1100 *
b10011100 $
b10011100 '
b1001110 #
b1001110 &
#395
b1100 "
b1100 *
b10011110 $
b10011110 '
b1001111 #
b1001111 &
#400
b1100 "
b1100 *
b10100000 $
b10100000 '
b1010000 #
b1010000 &
b100 %
b100 (
