lab1/mux.v
module MUX_6_TO_1
(
	input [7:0] d0, d1, d2, d3, d4, d5,
	input [2:0] sel,
	output reg [7:0] res
);

  always@(*) begin
    case (sel)
	  3'b000: res <= d0;
	  3'b001: res <= d1;
	  3'b010: res <= d2;
	  3'b011: res <= d3;
	  3'b100: res <= d4;
	  3'b101: res <= d5;
	  default: res <= 8'bzzzz_zzzz;
	endcase
  end

endmodule

lab1/mux_tb.v
`timescale 1ns/1ns

module MUX_6_TO_1_TB();

  reg [7:0] d0, d1, d2, d3, d4, d5;
  reg [2:0] sel;
  wire [7:0] res;
  
  MUX_6_TO_1 mux( .d0(d0), .d1(d1), .d2(d2), .d3(d3), .d4(d4), .d5(d5), .sel(sel), .res(res) );
  
  initial begin
    $dumpfile("mux_tb_out.vcd");
    $dumpvars(0, MUX_6_TO_1_TB);
  end

  initial begin
    d0 = 10; d1 = 20; d2 = 30; d3 = 40; d4 = 50; d5 = 60;
    sel = 3'b000;
  end  
  
  always #1 sel = sel + 1;
  
  initial begin
	#5;
	d0 = 100;
	d2 = 33;
  end
  
  initial begin
	#16; $finish;
  end

endmodule

lab1/mux_tb_out.vcd
$date
	Sun Nov 05 18:58:03 2023
$end
$version
	Icarus Verilog
$end
$timescale
	1ns
$end
$scope module MUX_6_TO_1_TB $end
$var wire 8 ! res [7:0] $end
$var reg 8 " d0 [7:0] $end
$var reg 8 # d1 [7:0] $end
$var reg 8 $ d2 [7:0] $end
$var reg 8 % d3 [7:0] $end
$var reg 8 & d4 [7:0] $end
$var reg 8 ' d5 [7:0] $end
$var reg 3 ( sel [2:0] $end
$scope module mux $end
$var wire 8 ) d0 [7:0] $end
$var wire 8 * d1 [7:0] $end
$var wire 8 + d2 [7:0] $end
$var wire 8 , d3 [7:0] $end
$var wire 8 - d4 [7:0] $end
$var wire 8 . d5 [7:0] $end
$var wire 3 / sel [2:0] $end
$var reg 8 0 res [7:0] $end
$upscope $end
$upscope $end
$enddefinitions $end
#0
$dumpvars
b1010 0
b0 /
b111100 .
b110010 -
b101000 ,
b11110 +
b10100 *
b1010 )
b0 (
b111100 '
b110010 &
b101000 %
b11110 $
b10100 #
b1010 "
b1010 !
$end
#1
b10100 !
b10100 0
b1 (
b1 /
#2
b11110 !
b11110 0
b10 (
b10 /
#3
b101000 !
b101000 0
b11 (
b11 /
#4
b110010 !
b110010 0
b100 (
b100 /
#5
b111100 !
b111100 0
b101 (
b101 /
b100001 $
b100001 +
b1100100 "
b1100100 )
#6
bz !
bz 0
b110 (
b110 /
#7
b111 (
b111 /
#8
b1100100 !
b1100100 0
b0 (
b0 /
#9
b10100 !
b10100 0
b1 (
b1 /
#10
b100001 !
b100001 0
b10 (
b10 /
#11
b101000 !
b101000 0
b11 (
b11 /
#12
b110010 !
b110010 0
b100 (
b100 /
#13
b111100 !
b111100 0
b101 (
b101 /
#14
bz !
bz 0
b110 (
b110 /
#15
b111 (
b111 /
#16
b1100100 !
b1100100 0
b0 (
b0 /
