lab4/maj.v
module MAJORITY_17
(
	input [16:0] in,
	output reg out
);
    
  reg [4:0] true_counter;
  integer i;
	
  always@(*) begin
	
	true_counter = 0;
	
	for (i = 0; i < 17; i = i + 1) begin		// count all the 1s in input
	  if (in[i] == 1'b1)
	    true_counter = true_counter + 1;
	end
	
	if (true_counter > 8)
	  out = 1;
	else
	  out = 0;
	
  end

endmodule

lab4/maj_tb.v
`timescale 1ns/1ns

module MAJORITY_17_TB();

  reg [16:0] in;
  wire out;
  
  MAJORITY_17 majority_17( .in(in), .out(out) );
  
  initial begin
    $dumpfile("maj_17_tb_out.vcd");
    $dumpvars(0, MAJORITY_17_TB);
  end

  localparam period = 5;
  
  always #period in = in + 3121;

  initial begin
	in = 0;
	#200;
	$finish;
  end

endmodule

lab4/maj_17_tb_out.vcd
$date
	Sun Nov 05 19:54:28 2023
$end
$version
	Icarus Verilog
$end
$timescale
	1ns
$end
$scope module MAJORITY_17_TB $end
$var wire 1 ! out $end
$var reg 17 " in [16:0] $end
$scope module majority_17 $end
$var wire 17 # in [16:0] $end
$var reg 1 ! out $end
$var reg 5 $ true_counter [4:0] $end
$var integer 32 % i [31:0] $end
$upscope $end
$upscope $end
$enddefinitions $end
#0
$dumpvars
b10001 %
b0 $
b0 #
b0 "
0!
$end
#5
b101 $
b10001 %
b110000110001 "
b110000110001 #
#10
b10001 %
b101 $
b1100001100010 "
b1100001100010 #
#15
b10001 %
b110 $
b10010010010011 "
b10010010010011 #
#20
b10001 %
b101 $
b11000011000100 "
b11000011000100 #
#25
1!
b10001 %
b1010 $
b11110011110101 "
b11110011110101 #
#30
0!
b10001 %
b110 $
b100100100100110 "
b100100100100110 #
#35
1!
b10001 %
b1001 $
b101010101010111 "
b101010101010111 #
#40
0!
b10001 %
b101 $
b110000110001000 "
b110000110001000 #
#45
1!
b10001 %
b1010 $
b110110110111001 "
b110110110111001 #
#50
b10001 %
b1010 $
b111100111101010 "
b111100111101010 #
#55
0!
b10001 %
b111 $
b1000011000011011 "
b1000011000011011 #
#60
b10001 %
b110 $
b1001001001001100 "
b1001001001001100 #
#65
1!
b10001 %
b1011 $
b1001111001111101 "
b1001111001111101 #
#70
b10001 %
b1001 $
b1010101010101110 "
b1010101010101110 #
#75
b10001 %
b1100 $
b1011011011011111 "
b1011011011011111 #
#80
0!
b10001 %
b101 $
b1100001100010000 "
b1100001100010000 #
#85
b10001 %
b1000 $
b1100111101000001 "
b1100111101000001 #
#90
1!
b10001 %
b1010 $
b1101101101110010 "
b1101101101110010 #
#95
b10001 %
b1010 $
b1110011110100011 "
b1110011110100011 #
#100
b10001 %
b1010 $
b1111001111010100 "
b1111001111010100 #
#105
0!
b10001 %
b11 $
b10000000000000101 "
b10000000000000101 #
#110
b10001 %
b111 $
b10000110000110110 "
b10000110000110110 #
#115
b10001 %
b1000 $
b10001100001100111 "
b10001100001100111 #
#120
b10001 %
b110 $
b10010010010011000 "
b10010010010011000 #
#125
b10001 %
b111 $
b10011000011001001 "
b10011000011001001 #
#130
1!
b10001 %
b1011 $
b10011110011111010 "
b10011110011111010 #
#135
0!
b10001 %
b1000 $
b10100100100101011 "
b10100100100101011 #
#140
1!
b10001 %
b1001 $
b10101010101011100 "
b10101010101011100 #
#145
0!
b10001 %
b1000 $
b10110000110001101 "
b10110000110001101 #
#150
1!
b10001 %
b1100 $
b10110110110111110 "
b10110110110111110 #
#155
b10001 %
b1101 $
b10111100111101111 "
b10111100111101111 #
#160
0!
b10001 %
b101 $
b11000011000100000 "
b11000011000100000 #
#165
b10001 %
b111 $
b11001001001010001 "
b11001001001010001 #
#170
b10001 %
b1000 $
b11001111010000010 "
b11001111010000010 #
#175
1!
b10001 %
b1010 $
b11010101010110011 "
b11010101010110011 #
#180
b10001 %
b1010 $
b11011011011100100 "
b11011011011100100 #
#185
0!
b10001 %
b1000 $
b11100001100010101 "
b11100001100010101 #
#190
1!
b10001 %
b1010 $
b11100111101000110 "
b11100111101000110 #
#195
b10001 %
b1101 $
b11101101101110111 "
b11101101101110111 #
#200
b10001 %
b1010 $
b11110011110101000 "
b11110011110101000 #
