lab5/counter.v
module COUNTER
(
	input clk,
	input reset,
	output reg [4:0] count
);
	
  always@(posedge clk or posedge reset) begin
	
	if (reset)					// Reset
	  count <= 17;
	else if (count == 0)		// Enable signal
	  count <= 17;
	else
	  count <= count - 1;
	
  end

endmodule

lab5/counter_tb.v
`timescale 1ns/1ns

module COUNTER_TB();

  reg clk;
  reg in;
  wire [4:0] out;
  
  COUNTER counter( .clk(clk), .reset(in), .count(out) );
  
  initial begin
    $dumpfile("counter_tb_out.vcd");
    $dumpvars(0, COUNTER_TB);
  end
  
  always #1 clk = ~clk;
  
  initial begin
	clk = 0;
	in = 0;
	
	#1;
	in = 1;
	
	#1;
	in = 0;
	
	#45;
	in = 1;
	
	#5;
	in = 0;
	
	#10;
	$finish;
  end

endmodule

lab5/counter_tb_out.vcd
$date
	Tue Nov 07 11:47:28 2023
$end
$version
	Icarus Verilog
$end
$timescale
	1ns
$end
$scope module COUNTER_TB $end
$var wire 5 ! out [4:0] $end
$var reg 1 " clk $end
$var reg 1 # in $end
$scope module counter $end
$var wire 1 " clk $end
$var wire 1 # reset $end
$var reg 5 $ count [4:0] $end
$upscope $end
$upscope $end
$enddefinitions $end
#0
$dumpvars
bx $
0#
0"
bx !
$end
#1
b10001 !
b10001 $
1#
1"
#2
0#
0"
#3
b10000 !
b10000 $
1"
#4
0"
#5
b1111 !
b1111 $
1"
#6
0"
#7
b1110 !
b1110 $
1"
#8
0"
#9
b1101 !
b1101 $
1"
#10
0"
#11
b1100 !
b1100 $
1"
#12
0"
#13
b1011 !
b1011 $
1"
#14
0"
#15
b1010 !
b1010 $
1"
#16
0"
#17
b1001 !
b1001 $
1"
#18
0"
#19
b1000 !
b1000 $
1"
#20
0"
#21
b111 !
b111 $
1"
#22
0"
#23
b110 !
b110 $
1"
#24
0"
#25
b101 !
b101 $
1"
#26
0"
#27
b100 !
b100 $
1"
#28
0"
#29
b11 !
b11 $
1"
#30
0"
#31
b10 !
b10 $
1"
#32
0"
#33
b1 !
b1 $
1"
#34
0"
#35
b0 !
b0 $
1"
#36
0"
#37
b10001 !
b10001 $
1"
#38
0"
#39
b10000 !
b10000 $
1"
#40
0"
#41
b1111 !
b1111 $
1"
#42
0"
#43
b1110 !
b1110 $
1"
#44
0"
#45
b1101 !
b1101 $
1"
#46
0"
#47
b10001 !
b10001 $
1"
1#
#48
0"
#49
1"
#50
0"
#51
1"
#52
0"
0#
#53
b10000 !
b10000 $
1"
#54
0"
#55
b1111 !
b1111 $
1"
#56
0"
#57
b1110 !
b1110 $
1"
#58
0"
#59
b1101 !
b1101 $
1"
#60
0"
#61
b1100 !
b1100 $
1"
