lab2/dec.v
module DECODER_3_TO_5
(
	input [2:0] in,
	output reg d0, d1, d2, d3, d4
);

  always@(*) begin
    d0 <= 0;
	d1 <= 0;
	d2 <= 0;
	d3 <= 0;
	d4 <= 0;
	
    case (in)
	  3'b000: d0 <= 1;
	  3'b001: d1 <= 1;
	  3'b010: d2 <= 1;
	  3'b011: d3 <= 1;
	  3'b100: d4 <= 1;
	endcase
  end

endmodule

lab2/dec_tb.v
`timescale 1ns/1ns

module DECODER_3_TO_5_TB();

  wire d0, d1, d2, d3, d4;
  reg [2:0] in;
  
  DECODER_3_TO_5 decoder( .in(in), .d0(d0), .d1(d1), .d2(d2), .d3(d3), .d4(d4) );
  
  initial begin
    $dumpfile("dec_tb_out.vcd");
    $dumpvars(0, DECODER_3_TO_5_TB);
  end

  always #1 in = in + 1;

  initial begin
	in = 3'b000;
	#16;
	$finish;
  end

endmodule

lab2/dec_tb_out.vcd
$date
	Sun Nov 05 19:02:39 2023
$end
$version
	Icarus Verilog
$end
$timescale
	1ns
$end
$scope module DECODER_3_TO_5_TB $end
$var wire 1 ! d4 $end
$var wire 1 " d3 $end
$var wire 1 # d2 $end
$var wire 1 $ d1 $end
$var wire 1 % d0 $end
$var reg 3 & in [2:0] $end
$scope module decoder $end
$var wire 3 ' in [2:0] $end
$var reg 1 % d0 $end
$var reg 1 $ d1 $end
$var reg 1 # d2 $end
$var reg 1 " d3 $end
$var reg 1 ! d4 $end
$upscope $end
$upscope $end
$enddefinitions $end
#0
$dumpvars
b0 '
b0 &
1%
0$
0#
0"
0!
$end
#1
1$
0%
b1 &
b1 '
#2
1#
0$
b10 &
b10 '
#3
1"
0#
b11 &
b11 '
#4
1!
0"
b100 &
b100 '
#5
0!
b101 &
b101 '
#6
b110 &
b110 '
#7
b111 &
b111 '
#8
1%
b0 &
b0 '
#9
1$
0%
b1 &
b1 '
#10
1#
0$
b10 &
b10 '
#11
1"
0#
b11 &
b11 '
#12
1!
0"
b100 &
b100 '
#13
0!
b101 &
b101 '
#14
b110 &
b110 '
#15
b111 &
b111 '
#16
1%
b0 &
b0 '
