lab2/dec.v
module DECODER_3_TO_5
(
	input [2:0] in,
	output reg d0, d1, d2, d3, d4
);

  always@(*) begin
    d0 <= 0;
	d1 <= 0;
	d2 <= 0;
	d3 <= 0;
	d4 <= 0;
	
    case (in)
	  3'b000: d0 <= 1;
	  3'b001: d1 <= 1;
	  3'b010: d2 <= 1;
	  3'b011: d3 <= 1;
	  3'b100: d4 <= 1;
	endcase
  end

endmodule

lab2/dec_tb.v
`timescale 1ns/1ns

module DECODER_3_TO_5_TB();

  wire d0, d1, d2, d3, d4;
  reg [2:0] in;
  
  DECODER_3_TO_5 decoder( .in(in), .d0(d0), .d1(d1), .d2(d2), .d3(d3), .d4(d4) );
  
  initial begin
    $dumpfile("dec_tb_out.vcd");
    $dumpvars(0, DECODER_3_TO_5_TB);
  end

  localparam period = 5;

  initial begin
	repeat (2) begin 
		in = 3'b000;
		
		#period;
		in = 3'b001;
		
		#period;
		in = 3'b010;
		
		#period;
		in = 3'b011;
		
		#period;
		in = 3'b100;
		
		#period;
		in = 3'b101;
		
		#period;
	end
	
	$finish;
  end

endmodule

lab2/dec_tb_out.vcd
$date
	Mon Oct 16 18:18:46 2023
$end
$version
	Icarus Verilog
$end
$timescale
	1ns
$end
$scope module DECODER_3_TO_5_TB $end
$var wire 1 ! d4 $end
$var wire 1 " d3 $end
$var wire 1 # d2 $end
$var wire 1 $ d1 $end
$var wire 1 % d0 $end
$var reg 3 & in [2:0] $end
$scope module decoder $end
$var wire 3 ' in [2:0] $end
$var reg 1 % d0 $end
$var reg 1 $ d1 $end
$var reg 1 # d2 $end
$var reg 1 " d3 $end
$var reg 1 ! d4 $end
$upscope $end
$upscope $end
$enddefinitions $end
#0
$dumpvars
b0 '
b0 &
1%
0$
0#
0"
0!
$end
#5
1$
0%
b1 &
b1 '
#10
1#
0$
b10 &
b10 '
#15
1"
0#
b11 &
b11 '
#20
1!
0"
b100 &
b100 '
#25
0!
b101 &
b101 '
#30
1%
b0 &
b0 '
#35
1$
0%
b1 &
b1 '
#40
1#
0$
b10 &
b10 '
#45
1"
0#
b11 &
b11 '
#50
1!
0"
b100 &
b100 '
#55
0!
b101 &
b101 '
