lab7/mux_4_to_1.v
module MUX_4_TO_1
(
	input [7:0] d0, d1, d2, d3,
	input [1:0] sel,
	output reg [7:0] result
);
	
  always@(*) begin
	case (sel)
	  2'b00: result <= d0;
	  2'b01: result <= d1;
	  2'b10: result <= d2;
	  2'b11: result <= d3;
	endcase
  end

endmodule

lab7/mux_16_to_1.v
module MUX_16_TO_1
(
	input [7:0] d0, d1, d2, d3, d4, d5, d6, d7, d8, d9, d10, d11, d12, d13, d14, d15,
	input [3:0] sel,
	output [7:0] result
);
	
  wire [7:0] g1_out, g2_out, g3_out, g4_out;
	
  MUX_4_TO_1 gate1( .d0(d0), .d1(d1), .d2(d2), .d3(d3), .sel(sel[1:0]), .result(g1_out) );
  
  MUX_4_TO_1 gate2( .d0(d4), .d1(d5), .d2(d6), .d3(d7), .sel(sel[1:0]), .result(g2_out) );
  
  MUX_4_TO_1 gate3( .d0(d8), .d1(d9), .d2(d10), .d3(d11), .sel(sel[1:0]), .result(g3_out) );
  
  MUX_4_TO_1 gate4( .d0(d12), .d1(d13), .d2(d14), .d3(d15), .sel(sel[1:0]), .result(g4_out) );
  
  MUX_4_TO_1 final_gate( .d0(g1_out), .d1(g2_out), .d2(g3_out), .d3(g4_out), .sel(sel[3:2]), .result(result) );

endmodule

lab7/mux_16_to_1_tb.v
`timescale 1ns/1ns

module MUX_16_TO_1_TB();

  reg [7:0] d0, d1, d2, d3, d4, d5, d6, d7, d8, d9, d10, d11, d12, d13, d14, d15;
  reg [3:0] sel;
  wire [7:0] res;
  
  MUX_16_TO_1 mux( .d0(d0), .d1(d1), .d2(d2), .d3(d3), .d4(d4), .d5(d5), .d6(d6), .d7(d7), .d8(d8), .d9(d9), .d10(d10), .d11(d11), .d12(d12), .d13(d13), .d14(d14), .d15(d15), .sel(sel), .result(res) );
  
  initial begin
    $dumpfile("mux_16_to_1_tb_out.vcd");
    $dumpvars(0, MUX_16_TO_1_TB);
  end

  initial begin
    d0 = 0; d1 = 10; d2 = 20; d3 = 30; 
	d4 = 40; d5 = 50; d6 = 60; d7 = 70; 
	d8 = 80; d9 = 90; d10 = 100; d11 = 110; 
	d12 = 120; d13 = 130; d14 = 140; d15 = 150;
    sel = 3'b000;
  end  
  
  always #1 sel = sel + 1;
  
  initial begin
	#10;
	d0 = 77;
	d2 = 33;
  end
  
  initial begin
	#40; $finish;
  end

endmodule

lab7/mux_16_to_1_tb_out.vcd
$date
	Mon Nov 20 21:11:26 2023
$end
$version
	Icarus Verilog
$end
$timescale
	1ns
$end
$scope module MUX_16_TO_1_TB $end
$var wire 8 ! res [7:0] $end
$var reg 8 " d0 [7:0] $end
$var reg 8 # d1 [7:0] $end
$var reg 8 $ d10 [7:0] $end
$var reg 8 % d11 [7:0] $end
$var reg 8 & d12 [7:0] $end
$var reg 8 ' d13 [7:0] $end
$var reg 8 ( d14 [7:0] $end
$var reg 8 ) d15 [7:0] $end
$var reg 8 * d2 [7:0] $end
$var reg 8 + d3 [7:0] $end
$var reg 8 , d4 [7:0] $end
$var reg 8 - d5 [7:0] $end
$var reg 8 . d6 [7:0] $end
$var reg 8 / d7 [7:0] $end
$var reg 8 0 d8 [7:0] $end
$var reg 8 1 d9 [7:0] $end
$var reg 4 2 sel [3:0] $end
$scope module mux $end
$var wire 8 3 d0 [7:0] $end
$var wire 8 4 d1 [7:0] $end
$var wire 8 5 d10 [7:0] $end
$var wire 8 6 d11 [7:0] $end
$var wire 8 7 d12 [7:0] $end
$var wire 8 8 d13 [7:0] $end
$var wire 8 9 d14 [7:0] $end
$var wire 8 : d15 [7:0] $end
$var wire 8 ; d2 [7:0] $end
$var wire 8 < d3 [7:0] $end
$var wire 8 = d4 [7:0] $end
$var wire 8 > d5 [7:0] $end
$var wire 8 ? d6 [7:0] $end
$var wire 8 @ d7 [7:0] $end
$var wire 8 A d8 [7:0] $end
$var wire 8 B d9 [7:0] $end
$var wire 4 C sel [3:0] $end
$var wire 8 D result [7:0] $end
$var wire 8 E g4_out [7:0] $end
$var wire 8 F g3_out [7:0] $end
$var wire 8 G g2_out [7:0] $end
$var wire 8 H g1_out [7:0] $end
$scope module final_gate $end
$var wire 2 I sel [1:0] $end
$var wire 8 J d3 [7:0] $end
$var wire 8 K d2 [7:0] $end
$var wire 8 L d1 [7:0] $end
$var wire 8 M d0 [7:0] $end
$var reg 8 N result [7:0] $end
$upscope $end
$scope module gate1 $end
$var wire 8 O d0 [7:0] $end
$var wire 8 P d1 [7:0] $end
$var wire 8 Q d2 [7:0] $end
$var wire 8 R d3 [7:0] $end
$var wire 2 S sel [1:0] $end
$var reg 8 T result [7:0] $end
$upscope $end
$scope module gate2 $end
$var wire 8 U d0 [7:0] $end
$var wire 8 V d1 [7:0] $end
$var wire 8 W d2 [7:0] $end
$var wire 8 X d3 [7:0] $end
$var wire 2 Y sel [1:0] $end
$var reg 8 Z result [7:0] $end
$upscope $end
$scope module gate3 $end
$var wire 8 [ d0 [7:0] $end
$var wire 8 \ d1 [7:0] $end
$var wire 8 ] d2 [7:0] $end
$var wire 8 ^ d3 [7:0] $end
$var wire 2 _ sel [1:0] $end
$var reg 8 ` result [7:0] $end
$upscope $end
$scope module gate4 $end
$var wire 8 a d0 [7:0] $end
$var wire 8 b d1 [7:0] $end
$var wire 8 c d2 [7:0] $end
$var wire 8 d d3 [7:0] $end
$var wire 2 e sel [1:0] $end
$var reg 8 f result [7:0] $end
$upscope $end
$upscope $end
$upscope $end
$enddefinitions $end
#0
$dumpvars
b1111000 f
b0 e
b10010110 d
b10001100 c
b10000010 b
b1111000 a
b1010000 `
b0 _
b1101110 ^
b1100100 ]
b1011010 \
b1010000 [
b101000 Z
b0 Y
b1000110 X
b111100 W
b110010 V
b101000 U
b0 T
b0 S
b11110 R
b10100 Q
b1010 P
b0 O
b0 N
b0 M
b101000 L
b1010000 K
b1111000 J
b0 I
b0 H
b101000 G
b1010000 F
b1111000 E
b0 D
b0 C
b1011010 B
b1010000 A
b1000110 @
b111100 ?
b110010 >
b101000 =
b11110 <
b10100 ;
b10010110 :
b10001100 9
b10000010 8
b1111000 7
b1101110 6
b1100100 5
b1010 4
b0 3
b0 2
b1011010 1
b1010000 0
b1000110 /
b111100 .
b110010 -
b101000 ,
b11110 +
b10100 *
b10010110 )
b10001100 (
b10000010 '
b1111000 &
b1101110 %
b1100100 $
b1010 #
b0 "
b0 !
$end
#1
b1010 !
b1010 D
b1010 N
b1010 H
b1010 M
b1010 T
b110010 G
b110010 L
b110010 Z
b1011010 F
b1011010 K
b1011010 `
b10000010 E
b10000010 J
b10000010 f
b1 S
b1 Y
b1 _
b1 e
b1 2
b1 C
#2
b10100 !
b10100 D
b10100 N
b10100 H
b10100 M
b10100 T
b111100 G
b111100 L
b111100 Z
b1100100 F
b1100100 K
b1100100 `
b10001100 E
b10001100 J
b10001100 f
b10 S
b10 Y
b10 _
b10 e
b10 2
b10 C
#3
b11110 !
b11110 D
b11110 N
b11110 H
b11110 M
b11110 T
b1000110 G
b1000110 L
b1000110 Z
b1101110 F
b1101110 K
b1101110 `
b10010110 E
b10010110 J
b10010110 f
b11 S
b11 Y
b11 _
b11 e
b11 2
b11 C
#4
b0 H
b0 M
b0 T
b101000 G
b101000 L
b101000 Z
b1010000 F
b1010000 K
b1010000 `
b1111000 E
b1111000 J
b1111000 f
b101000 !
b101000 D
b101000 N
b0 S
b0 Y
b0 _
b0 e
b1 I
b100 2
b100 C
#5
b110010 !
b110010 D
b110010 N
b1010 H
b1010 M
b1010 T
b110010 G
b110010 L
b110010 Z
b1011010 F
b1011010 K
b1011010 `
b10000010 E
b10000010 J
b10000010 f
b1 S
b1 Y
b1 _
b1 e
b101 2
b101 C
#6
b111100 !
b111100 D
b111100 N
b10100 H
b10100 M
b10100 T
b111100 G
b111100 L
b111100 Z
b1100100 F
b1100100 K
b1100100 `
b10001100 E
b10001100 J
b10001100 f
b10 S
b10 Y
b10 _
b10 e
b110 2
b110 C
#7
b1000110 !
b1000110 D
b1000110 N
b11110 H
b11110 M
b11110 T
b1000110 G
b1000110 L
b1000110 Z
b1101110 F
b1101110 K
b1101110 `
b10010110 E
b10010110 J
b10010110 f
b11 S
b11 Y
b11 _
b11 e
b111 2
b111 C
#8
b0 H
b0 M
b0 T
b101000 G
b101000 L
b101000 Z
b1010000 F
b1010000 K
b1010000 `
b1111000 E
b1111000 J
b1111000 f
b1010000 !
b1010000 D
b1010000 N
b0 S
b0 Y
b0 _
b0 e
b10 I
b1000 2
b1000 C
#9
b1011010 !
b1011010 D
b1011010 N
b1010 H
b1010 M
b1010 T
b110010 G
b110010 L
b110010 Z
b1011010 F
b1011010 K
b1011010 `
b10000010 E
b10000010 J
b10000010 f
b1 S
b1 Y
b1 _
b1 e
b1001 2
b1001 C
#10
b1100100 !
b1100100 D
b1100100 N
b100001 H
b100001 M
b100001 T
b111100 G
b111100 L
b111100 Z
b1100100 F
b1100100 K
b1100100 `
b10001100 E
b10001100 J
b10001100 f
b10 S
b10 Y
b10 _
b10 e
b1010 2
b1010 C
b100001 *
b100001 ;
b100001 Q
b1001101 "
b1001101 3
b1001101 O
#11
b1101110 !
b1101110 D
b1101110 N
b11110 H
b11110 M
b11110 T
b1000110 G
b1000110 L
b1000110 Z
b1101110 F
b1101110 K
b1101110 `
b10010110 E
b10010110 J
b10010110 f
b11 S
b11 Y
b11 _
b11 e
b1011 2
b1011 C
#12
b1001101 H
b1001101 M
b1001101 T
b101000 G
b101000 L
b101000 Z
b1010000 F
b1010000 K
b1010000 `
b1111000 E
b1111000 J
b1111000 f
b1111000 !
b1111000 D
b1111000 N
b0 S
b0 Y
b0 _
b0 e
b11 I
b1100 2
b1100 C
#13
b10000010 !
b10000010 D
b10000010 N
b1010 H
b1010 M
b1010 T
b110010 G
b110010 L
b110010 Z
b1011010 F
b1011010 K
b1011010 `
b10000010 E
b10000010 J
b10000010 f
b1 S
b1 Y
b1 _
b1 e
b1101 2
b1101 C
#14
b10001100 !
b10001100 D
b10001100 N
b100001 H
b100001 M
b100001 T
b111100 G
b111100 L
b111100 Z
b1100100 F
b1100100 K
b1100100 `
b10001100 E
b10001100 J
b10001100 f
b10 S
b10 Y
b10 _
b10 e
b1110 2
b1110 C
#15
b10010110 !
b10010110 D
b10010110 N
b11110 H
b11110 M
b11110 T
b1000110 G
b1000110 L
b1000110 Z
b1101110 F
b1101110 K
b1101110 `
b10010110 E
b10010110 J
b10010110 f
b11 S
b11 Y
b11 _
b11 e
b1111 2
b1111 C
#16
b1001101 H
b1001101 M
b1001101 T
b101000 G
b101000 L
b101000 Z
b1010000 F
b1010000 K
b1010000 `
b1111000 E
b1111000 J
b1111000 f
b1001101 !
b1001101 D
b1001101 N
b0 S
b0 Y
b0 _
b0 e
b0 I
b0 2
b0 C
#17
b1010 !
b1010 D
b1010 N
b1010 H
b1010 M
b1010 T
b110010 G
b110010 L
b110010 Z
b1011010 F
b1011010 K
b1011010 `
b10000010 E
b10000010 J
b10000010 f
b1 S
b1 Y
b1 _
b1 e
b1 2
b1 C
#18
b100001 !
b100001 D
b100001 N
b100001 H
b100001 M
b100001 T
b111100 G
b111100 L
b111100 Z
b1100100 F
b1100100 K
b1100100 `
b10001100 E
b10001100 J
b10001100 f
b10 S
b10 Y
b10 _
b10 e
b10 2
b10 C
#19
b11110 !
b11110 D
b11110 N
b11110 H
b11110 M
b11110 T
b1000110 G
b1000110 L
b1000110 Z
b1101110 F
b1101110 K
b1101110 `
b10010110 E
b10010110 J
b10010110 f
b11 S
b11 Y
b11 _
b11 e
b11 2
b11 C
#20
b1001101 H
b1001101 M
b1001101 T
b101000 G
b101000 L
b101000 Z
b1010000 F
b1010000 K
b1010000 `
b1111000 E
b1111000 J
b1111000 f
b101000 !
b101000 D
b101000 N
b0 S
b0 Y
b0 _
b0 e
b1 I
b100 2
b100 C
#21
b110010 !
b110010 D
b110010 N
b1010 H
b1010 M
b1010 T
b110010 G
b110010 L
b110010 Z
b1011010 F
b1011010 K
b1011010 `
b10000010 E
b10000010 J
b10000010 f
b1 S
b1 Y
b1 _
b1 e
b101 2
b101 C
#22
b111100 !
b111100 D
b111100 N
b100001 H
b100001 M
b100001 T
b111100 G
b111100 L
b111100 Z
b1100100 F
b1100100 K
b1100100 `
b10001100 E
b10001100 J
b10001100 f
b10 S
b10 Y
b10 _
b10 e
b110 2
b110 C
#23
b1000110 !
b1000110 D
b1000110 N
b11110 H
b11110 M
b11110 T
b1000110 G
b1000110 L
b1000110 Z
b1101110 F
b1101110 K
b1101110 `
b10010110 E
b10010110 J
b10010110 f
b11 S
b11 Y
b11 _
b11 e
b111 2
b111 C
#24
b1001101 H
b1001101 M
b1001101 T
b101000 G
b101000 L
b101000 Z
b1010000 F
b1010000 K
b1010000 `
b1111000 E
b1111000 J
b1111000 f
b1010000 !
b1010000 D
b1010000 N
b0 S
b0 Y
b0 _
b0 e
b10 I
b1000 2
b1000 C
#25
b1011010 !
b1011010 D
b1011010 N
b1010 H
b1010 M
b1010 T
b110010 G
b110010 L
b110010 Z
b1011010 F
b1011010 K
b1011010 `
b10000010 E
b10000010 J
b10000010 f
b1 S
b1 Y
b1 _
b1 e
b1001 2
b1001 C
#26
b1100100 !
b1100100 D
b1100100 N
b100001 H
b100001 M
b100001 T
b111100 G
b111100 L
b111100 Z
b1100100 F
b1100100 K
b1100100 `
b10001100 E
b10001100 J
b10001100 f
b10 S
b10 Y
b10 _
b10 e
b1010 2
b1010 C
#27
b1101110 !
b1101110 D
b1101110 N
b11110 H
b11110 M
b11110 T
b1000110 G
b1000110 L
b1000110 Z
b1101110 F
b1101110 K
b1101110 `
b10010110 E
b10010110 J
b10010110 f
b11 S
b11 Y
b11 _
b11 e
b1011 2
b1011 C
#28
b1001101 H
b1001101 M
b1001101 T
b101000 G
b101000 L
b101000 Z
b1010000 F
b1010000 K
b1010000 `
b1111000 E
b1111000 J
b1111000 f
b1111000 !
b1111000 D
b1111000 N
b0 S
b0 Y
b0 _
b0 e
b11 I
b1100 2
b1100 C
#29
b10000010 !
b10000010 D
b10000010 N
b1010 H
b1010 M
b1010 T
b110010 G
b110010 L
b110010 Z
b1011010 F
b1011010 K
b1011010 `
b10000010 E
b10000010 J
b10000010 f
b1 S
b1 Y
b1 _
b1 e
b1101 2
b1101 C
#30
b10001100 !
b10001100 D
b10001100 N
b100001 H
b100001 M
b100001 T
b111100 G
b111100 L
b111100 Z
b1100100 F
b1100100 K
b1100100 `
b10001100 E
b10001100 J
b10001100 f
b10 S
b10 Y
b10 _
b10 e
b1110 2
b1110 C
#31
b10010110 !
b10010110 D
b10010110 N
b11110 H
b11110 M
b11110 T
b1000110 G
b1000110 L
b1000110 Z
b1101110 F
b1101110 K
b1101110 `
b10010110 E
b10010110 J
b10010110 f
b11 S
b11 Y
b11 _
b11 e
b1111 2
b1111 C
#32
b1001101 H
b1001101 M
b1001101 T
b101000 G
b101000 L
b101000 Z
b1010000 F
b1010000 K
b1010000 `
b1111000 E
b1111000 J
b1111000 f
b1001101 !
b1001101 D
b1001101 N
b0 S
b0 Y
b0 _
b0 e
b0 I
b0 2
b0 C
#33
b1010 !
b1010 D
b1010 N
b1010 H
b1010 M
b1010 T
b110010 G
b110010 L
b110010 Z
b1011010 F
b1011010 K
b1011010 `
b10000010 E
b10000010 J
b10000010 f
b1 S
b1 Y
b1 _
b1 e
b1 2
b1 C
#34
b100001 !
b100001 D
b100001 N
b100001 H
b100001 M
b100001 T
b111100 G
b111100 L
b111100 Z
b1100100 F
b1100100 K
b1100100 `
b10001100 E
b10001100 J
b10001100 f
b10 S
b10 Y
b10 _
b10 e
b10 2
b10 C
#35
b11110 !
b11110 D
b11110 N
b11110 H
b11110 M
b11110 T
b1000110 G
b1000110 L
b1000110 Z
b1101110 F
b1101110 K
b1101110 `
b10010110 E
b10010110 J
b10010110 f
b11 S
b11 Y
b11 _
b11 e
b11 2
b11 C
#36
b1001101 H
b1001101 M
b1001101 T
b101000 G
b101000 L
b101000 Z
b1010000 F
b1010000 K
b1010000 `
b1111000 E
b1111000 J
b1111000 f
b101000 !
b101000 D
b101000 N
b0 S
b0 Y
b0 _
b0 e
b1 I
b100 2
b100 C
#37
b110010 !
b110010 D
b110010 N
b1010 H
b1010 M
b1010 T
b110010 G
b110010 L
b110010 Z
b1011010 F
b1011010 K
b1011010 `
b10000010 E
b10000010 J
b10000010 f
b1 S
b1 Y
b1 _
b1 e
b101 2
b101 C
#38
b111100 !
b111100 D
b111100 N
b100001 H
b100001 M
b100001 T
b111100 G
b111100 L
b111100 Z
b1100100 F
b1100100 K
b1100100 `
b10001100 E
b10001100 J
b10001100 f
b10 S
b10 Y
b10 _
b10 e
b110 2
b110 C
#39
b1000110 !
b1000110 D
b1000110 N
b11110 H
b11110 M
b11110 T
b1000110 G
b1000110 L
b1000110 Z
b1101110 F
b1101110 K
b1101110 `
b10010110 E
b10010110 J
b10010110 f
b11 S
b11 Y
b11 _
b11 e
b111 2
b111 C
#40
b1001101 H
b1001101 M
b1001101 T
b101000 G
b101000 L
b101000 Z
b1010000 F
b1010000 K
b1010000 `
b1111000 E
b1111000 J
b1111000 f
b1010000 !
b1010000 D
b1010000 N
b0 S
b0 Y
b0 _
b0 e
b10 I
b1000 2
b1000 C
